mini_maze/__init__.py
mini_maze/maze.py
mini_maze/maze_generator.py
mini_maze/mini_maze-updated.py
mini_maze/mini_maze.py
mini_maze-0.1.3.dist-info/LICENSE
mini_maze-0.1.3.dist-info/METADATA
mini_maze-0.1.3.dist-info/WHEEL
mini_maze-0.1.3.dist-info/top_level.txt
mini_maze-0.1.3.dist-info/RECORD
