Metadata-Version: 2.1
Name: mini-maze
Version: 0.1.3
Summary: A mini-maze environment for reinforcement learning experiments
Home-page: https://github.com/mshaocong/mini-maze
Author: Shaocong Ma
Author-email: scma0908@gmail.com
Classifier: Programming Language :: Python :: 3
Classifier: License :: OSI Approved :: MIT License
Classifier: Operating System :: OS Independent
Requires-Python: >=3.6
License-File: LICENSE
Requires-Dist: minigrid >=2.1.0
